Workbook

Sheet README
A1: Meta Platforms, Inc. - Annual Report data prepared for Power BI (Assignment 3)
A3: All currency values are US$ millions unless the column name says otherwise.
A4: Blue numbers = figures typed in from the source filings. Black numbers = formulas.
A5: Each sheet holds ONE Excel table (named tbl...). In Power BI: Get Data > Excel > tick the tbl... tables.
A7: SOURCES
A8: FY2025 & FY2024: Meta Form 10-K for year ended 31 Dec 2025 (filed 29 Jan 2026) and Q4/FY2025 results release (Exhibit 99.1, 28 Jan 2026).
A9: https://www.sec.gov/Archives/edgar/data/1326801/000162828026003942/meta-20251231.htm
A10: https://www.sec.gov/Archives/edgar/data/1326801/000162828026003832/meta-12312025xexhibit991.htm
A11: Geography 2021-2023: Meta Form 10-K FY2023 and FY2024 (revenue by customer address).
A12: 2021-2023 income statement, segment, cash-flow, DAP & headcount: Meta 10-Ks for FY2021-FY2023. Totals were cross-checked;
A13: spot-check these older rows against the filings before submitting (Item 7 & Item 8 of each 10-K).
A14: Quarterly 2025: Meta quarterly results releases (Q1-Q4 2025); quarters sum to the full-year totals.
... A19: Free cash flow = operating cash flow - purchases of property & equipment - principal payments on finance leases (Meta's current definition).

Sheet Income_Statement
A1: Year | B1: Revenue | C1: Cost_of_Revenue | D1: Gross_Profit | E1: R_and_D | F1: Marketing_and_Sales | G1: General_and_Admin | H1: Total_Costs_and_Expenses | I1: Operating_Income | J1: Interest_and_Other_Income | K1: Pretax_Income | L1: Income_Tax | M1: Net_Income | N1: Diluted_EPS_USD | O1: Diluted_Shares_mm
A2: 2021 | B2: 117929 | C2: 22649 | D2: =B2-C2 -> 95280 | E2: 24655 | F2: 14043 | G2: 9829 | H2: =C2+E2+F2+G2 -> 71176 | I2: =B2-H2 -> 46753 | J2: 531 | K2: =I2+J2 -> 47284 | L2: 7914 | M2: =K2-L2 -> 39370 | N2: 13.77 | O2: 2859
A3: 2022 | B3: 116609 | C3: 25249 | D3: =B3-C3 -> 91360 | E3: 35338 | F3: 15262 | G3: 11816 | H3: =C3+E3+F3+G3 -> 87665 | I3: =B3-H3 -> 28944 | J3: -125 | K3: =I3+J3 -> 28819 | L3: 5619 | M3: =K3-L3 -> 23200 | N3: 8.59 | O3: 2702
A4: 2023 | B4: 134902 | C4: 25959 | D4: =B4-C4 -> 108943 | E4: 38483 | F4: 12301 | G4: 11408 | H4: =C4+E4+F4+G4 -> 88151 | I4: =B4-H4 -> 46751 | J4: 677 | K4: =I4+J4 -> 47428 | L4: 8330 | M4: =K4-L4 -> 39098 | N4: 14.87 | O4: 2629
A5: 2024 | B5: 164501 | C5: 30161 | D5: =B5-C5 -> 134340 | E5: 43873 | F5: 11347 | G5: 9740 | H5: =C5+E5+F5+G5 -> 95121 | I5: =B5-H5 -> 69380 | J5: 1283 | K5: =I5+J5 -> 70663 | L5: 8303 | M5: =K5-L5 -> 62360 | N5: 23.86 | O5: 2614
A6: 2025 | B6: 200966 | C6: 36175 | D6: =B6-C6 -> 164791 | E6: 57372 | F6: 11991 | G6: 12152 | H6: =C6+E6+F6+G6 -> 117690 | I6: =B6-H6 -> 83276 | J6: 2656 | K6: =I6+J6 -> 85932 | L6: 25474 | M6: =K6-L6 -> 60458 | N6: 23.49 | O6: 2574

Sheet Segments
A1: Year | B1: Advertising_Revenue | C1: FoA_Other_Revenue | D1: Family_of_Apps_Revenue | E1: Reality_Labs_Revenue | F1: Total_Revenue | G1: FoA_Operating_Income | H1: RL_Operating_Income | I1: Total_Operating_Income | J1: FoA_Operating_Margin | K1: Advertising_Share_of_Revenue
A2: 2021 | B2: 114934 | C2: 721 | D2: =B2+C2 -> 115655 | E2: 2274 | F2: =D2+E2 -> 117929 | G2: 56946 | H2: -10193 | I2: =G2+H2 -> 46753 | J2: =G2/D2 -> 0.49237819 | K2: =B2/F2 -> 0.97460336
A3: 2022 | B3: 113642 | C3: 808 | D3: =B3+C3 -> 114450 | E3: 2159 | F3: =D3+E3 -> 116609 | G3: 42661 | H3: -13717 | I3: =G3+H3 -> 28944 | J3: =G3/D3 -> 0.37274792 | K3: =B3/F3 -> 0.97455599
A4: 2023 | B4: 131948 | C4: 1058 | D4: =B4+C4 -> 133006 | E4: 1896 | F4: =D4+E4 -> 134902 | G4: 62871 | H4: -16120 | I4: =G4+H4 -> 46751 | J4: =G4/D4 -> 0.47269296 | K4: =B4/F4 -> 0.97810262
A5: 2024 | B5: 160633 | C5: 1722 | D5: =B5+C5 -> 162355 | E5: 2146 | F5: =D5+E5 -> 164501 | G5: 87109 | H5: -17729 | I5: =G5+H5 -> 69380 | J5: =G5/D5 -> 0.53653414 | K5: =B5/F5 -> 0.97648647
A6: 2025 | B6: 196175 | C6: 2584 | D6: =B6+C6 -> 198759 | E6: 2207 | F6: =D6+E6 -> 200966 | G6: 102469 | H6: -19193 | I6: =G6+H6 -> 83276 | J6: =G6/D6 -> 0.51554395 | K6: =B6/F6 -> 0.97616015

Sheet Geography
A1: Year | B1: Region | C1: Revenue
A2: 2021 | B2: United States and Canada | C2: 51541
A3: 2021 | B3: Europe | C3: 29057
A4: 2021 | B4: Asia-Pacific | C4: 26739
A5: 2021 | B5: Rest of World | C5: 10592
A6: 2022 | B6: United States and Canada | C6: 50150
A7: 2022 | B7: Europe | C7: 26681
A8: 2022 | B8: Asia-Pacific | C8: 27760
A9: 2022 | B9: Rest of World | C9: 12018
A10: 2023 | B10: United States and Canada | C10: 52888
A11: 2023 | B11: Europe | C11: 31210
A12: 2023 | B12: Asia-Pacific | C12: 36154
A13: 2023 | B13: Rest of World | C13: 14650
... A21: 2025 | B21: Rest of World | C21: 21714

Sheet Balance_Sheet
A1: Year | B1: Class | C1: Section | D1: Line_Item | E1: Amount | G1: Check (Assets - Liabilities - Equity)
A2: 2025 | B2: Assets | C2: Current Assets | D2: Cash and cash equivalents | E2: 35873 | G2: 2025 | H2: =SUMIFS(E2:E39,A2:A39,G2,B2:B39,"Assets")-SUMIFS(E2:E39,A2:A39,G2,B2:B39,"Liabilities")-SUMIFS(E2:E39,A2:A39,G2,B2:B39,"Equity") -> 0
A3: 2025 | B3: Assets | C3: Current Assets | D3: Marketable securities | E3: 45719 | G3: 2024 | H3: =SUMIFS(E2:E39,A2:A39,G3,B2:B39,"Assets")-SUMIFS(E2:E39,A2:A39,G3,B2:B39,"Liabilities")-SUMIFS(E2:E39,A2:A39,G3,B2:B39,"Equity") -> 0
A4: 2025 | B4: Assets | C4: Current Assets | D4: Accounts receivable, net | E4: 19769
A5: 2025 | B5: Assets | C5: Current Assets | D5: Prepaid expenses and other current assets | E5: 7361
A6: 2025 | B6: Assets | C6: Non-current Assets | D6: Non-marketable equity investments | E6: 27524
A7: 2025 | B7: Assets | C7: Non-current Assets | D7: Property and equipment, net | E7: 176400
A8: 2025 | B8: Assets | C8: Non-current Assets | D8: Operating lease right-of-use assets | E8: 20404
A9: 2025 | B9: Assets | C9: Non-current Assets | D9: Goodwill | E9: 24534
A10: 2025 | B10: Assets | C10: Non-current Assets | D10: Other assets | E10: 8437
A11: 2025 | B11: Liabilities | C11: Current Liabilities | D11: Accounts payable | E11: 8894
A12: 2025 | B12: Liabilities | C12: Current Liabilities | D12: Operating lease liabilities, current | E12: 2213
A13: 2025 | B13: Liabilities | C13: Current Liabilities | D13: Accrued expenses and other current liabilities | E13: 30729
A14: 2025 | B14: Liabilities | C14: Non-current Liabilities | D14: Operating lease liabilities, non-current | E14: 22940
A15: 2025 | B15: Liabilities | C15: Non-current Liabilities | D15: Long-term debt | E15: 58744
... A39: 2024 | B39: Equity | C39: Equity | D39: Retained earnings | E39: 102506

Sheet Cash_Flow
A1: Year | B1: Operating_Cash_Flow | C1: Purchases_of_PPE | D1: Finance_Lease_Principal | E1: Total_Capex | F1: Free_Cash_Flow | G1: Share_Repurchases | H1: Dividends_Paid | I1: Total_Shareholder_Return | J1: Depreciation_and_Amortization | K1: Net_Income | L1: Cash_Conversion
A2: 2021 | B2: 57683 | C2: 18567 | D2: 677 | E2: =C2+D2 -> 19244 | F2: =B2-E2 -> 38439 | G2: 44537 | H2: 0 | I2: =G2+H2 -> 44537 | J2: 8025 | K2: 39370 | L2: =B2/K2 -> 1.4651511
A3: 2022 | B3: 50475 | C3: 31431 | D3: 850 | E3: =C3+D3 -> 32281 | F3: =B3-E3 -> 18194 | G3: 27956 | H3: 0 | I3: =G3+H3 -> 27956 | J3: 8686 | K3: 23200 | L3: =B3/K3 -> 2.1756466
A4: 2023 | B4: 71113 | C4: 27045 | D4: 1058 | E4: =C4+D4 -> 28103 | F4: =B4-E4 -> 43010 | G4: 19774 | H4: 0 | I4: =G4+H4 -> 19774 | J4: 11178 | K4: 39098 | L4: =B4/K4 -> 1.8188398
A5: 2024 | B5: 91328 | C5: 37256 | D5: 1969 | E5: =C5+D5 -> 39225 | F5: =B5-E5 -> 52103 | G5: 30125 | H5: 5072 | I5: =G5+H5 -> 35197 | J5: 15498 | K5: 62360 | L5: =B5/K5 -> 1.4645285
A6: 2025 | B6: 115800 | C6: 69691 | D6: 2524 | E6: =C6+D6 -> 72215 | F6: =B6-E6 -> 43585 | G6: 26248 | H6: 5324 | I6: =G6+H6 -> 31572 | J6: 18616 | K6: 60458 | L6: =B6/K6 -> 1.9153793

Sheet KPIs
A1: Year | B1: Daily_Active_People_bn | C1: Headcount | D1: Revenue | E1: Revenue_per_Employee_USD_k | F1: Revenue_per_DAP_USD
A2: 2021 | B2: 2.82 | C2: 71970 | D2: 117929 | E2: =D2/C2*1000 -> 1638.5855 | F2: =D2/(B2*1000) -> 41.818794
A3: 2022 | B3: 2.96 | C3: 86482 | D3: 116609 | E3: =D3/C3*1000 -> 1348.3615 | F3: =D3/(B3*1000) -> 39.394932
A4: 2023 | B4: 3.19 | C4: 67317 | D4: 134902 | E4: =D4/C4*1000 -> 2003.9812 | F4: =D4/(B4*1000) -> 42.289028
A5: 2024 | B5: 3.35 | C5: 74067 | D5: 164501 | E5: =D5/C5*1000 -> 2220.9756 | F5: =D5/(B5*1000) -> 49.104776
A6: 2025 | B6: 3.58 | C6: 78865 | D6: 200966 | E6: =D6/C6*1000 -> 2548.228 | F6: =D6/(B6*1000) -> 56.135754

Sheet Quarterly_2025
A1: Quarter | B1: Quarter_Order | C1: Revenue | D1: Operating_Income | E1: Net_Income | F1: Capex_USD_bn | G1: DAP_bn | H1: Operating_Margin
A2: Q1 2025 | B2: 1 | C2: 42314 | D2: 17555 | E2: 16644 | F2: 13.69 | G2: 3.43 | H2: =D2/C2 -> 0.41487451
A3: Q2 2025 | B3: 2 | C3: 47516 | D3: 20441 | E3: 18337 | F3: 17.01 | G3: 3.48 | H3: =D3/C3 -> 0.43019194
A4: Q3 2025 | B4: 3 | C4: 51242 | D4: 20535 | E4: 2709 | F4: 19.37 | G4: 3.54 | H4: =D4/C4 -> 0.40074548
A5: Q4 2025 | B5: 4 | C5: 59893 | D5: 24745 | E5: 22768 | F5: 22.14 | G5: 3.58 | H5: =D5/C5 -> 0.41315346

Sheet Investment_Split
A1: Category | B1: Item | C1: Value | E1: Values: US$ millions for 2025 rows; percent for 2026 plan rows (from 10-K Item 1).
A2: 2025 costs & expenses | B2: Family of Apps | C2: 96290
A3: 2025 costs & expenses | B3: Reality Labs | C3: 21400
A4: 2026 RL opex plan (%) | B4: Wearables | C4: 70
A5: 2026 RL opex plan (%) | B5: VR & Horizon | C5: 30

Sheet Ratios
A1: Year | B1: Revenue_Growth | C1: Gross_Margin | D1: Operating_Margin | E1: Net_Margin | F1: Effective_Tax_Rate | G1: RandD_pct_Revenue | H1: Capex_pct_Revenue | I1: FCF_Margin | K1: Balance-sheet ratios
A2: 2021 | C2: =Income_Statement!D2/Income_Statement!B2 -> 0.80794376 | D2: =Income_Statement!I2/Income_Statement!B2 -> 0.39645041 | E2: =Income_Statement!M2/Income_Statement!B2 -> 0.33384494 | F2: =Income_Statement!L2/Income_Statement!K2 -> 0.16737163 | G2: =Income_Statement!E2/Income_Statement!B2 -> 0.20906647 | H2: =Cash_Flow!E2/Income_Statement!B2 -> 0.16318293 | I2: =Cash_Flow!F2/Income_Statement!B2 -> 0.32595036 | L2: 2025 | M2: 2024
A3: 2022 | B3: =Income_Statement!B3/Income_Statement!B2-1 -> -0.011193176 | C3: =Income_Statement!D3/Income_Statement!B3 -> 0.78347297 | D3: =Income_Statement!I3/Income_Statement!B3 -> 0.24821412 | E3: =Income_Statement!M3/Income_Statement!B3 -> 0.19895548 | F3: =Income_Statement!L3/Income_Statement!K3 -> 0.19497554 | G3: =Income_Statement!E3/Income_Statement!B3 -> 0.30304693 | H3: =Cash_Flow!E3/Income_Statement!B3 -> 0.27683112 | I3: =Cash_Flow!F3/Income_Statement!B3 -> 0.15602569 | K3: Current ratio | L3: =SUMIFS(Balance_Sheet!E:E,Balance_Sheet!A:A,"2025",Balance_Sheet!C:C,"Current Assets")/SUMIFS(Balance_Sheet!E:E,Balance_Sheet!A:A,"2025",Balance_Sheet!C:C,"Current Liabilities") -> 2.5987666 | M3: =SUMIFS(Balance_Sheet!E:E,Balance_Sheet!A:A,"2024",Balance_Sheet!C:C,"Current Assets")/SUMIFS(Balance_Sheet!E:E,Balance_Sheet!A:A,"2024",Balance_Sheet!C:C,"Current Liabilities") -> 2.9778843
A4: 2023 | B4: =Income_Statement!B4/Income_Statement!B3-1 -> 0.15687468 | C4: =Income_Statement!D4/Income_Statement!B4 -> 0.80757142 | D4: =Income_Statement!I4/Income_Statement!B4 -> 0.34655528 | E4: =Income_Statement!M4/Income_Statement!B4 -> 0.28982521 | F4: =Income_Statement!L4/Income_Statement!K4 -> 0.17563465 | G4: =Income_Statement!E4/Income_Statement!B4 -> 0.28526634 | H4: =Cash_Flow!E4/Income_Statement!B4 -> 0.2083216 | I4: =Cash_Flow!F4/Income_Statement!B4 -> 0.31882404 | K4: Debt-to-equity | L4: =SUMIFS(Balance_Sheet!E:E,Balance_Sheet!A:A,"2025",Balance_Sheet!D:D,"Long-term debt")/SUMIFS(Balance_Sheet!E:E,Balance_Sheet!A:A,"2025",Balance_Sheet!B:B,"Equity") -> 0.27040687 | M4: =SUMIFS(Balance_Sheet!E:E,Balance_Sheet!A:A,"2024",Balance_Sheet!D:D,"Long-term debt")/SUMIFS(Balance_Sheet!E:E,Balance_Sheet!A:A,"2024",Balance_Sheet!B:B,"Equity") -> 0.1578322
A5: 2024 | B5: =Income_Statement!B5/Income_Statement!B4-1 -> 0.21941113 | C5: =Income_Statement!D5/Income_Statement!B5 -> 0.81665157 | D5: =Income_Statement!I5/Income_Statement!B5 -> 0.42176035 | E5: =Income_Statement!M5/Income_Statement!B5 -> 0.37908584 | F5: =Income_Statement!L5/Income_Statement!K5 -> 0.11750138 | G5: =Income_Statement!E5/Income_Statement!B5 -> 0.26670355 | H5: =Cash_Flow!E5/Income_Statement!B5 -> 0.2384484 | I5: =Cash_Flow!F5/Income_Statement!B5 -> 0.31673364 | K5: Return on equity (NI / closing equity) | L5: =INDEX(Income_Statement!M:M,MATCH("2025",Income_Statement!A:A,0))/SUMIFS(Balance_Sheet!E:E,Balance_Sheet!A:A,"2025",Balance_Sheet!B:B,"Equity") -> 0.27829665 | M5: =INDEX(Income_Statement!M:M,MATCH("2024",Income_Statement!A:A,0))/SUMIFS(Balance_Sheet!E:E,Balance_Sheet!A:A,"2024",Balance_Sheet!B:B,"Equity") -> 0.34144231
A6: 2025 | B6: =Income_Statement!B6/Income_Statement!B5-1 -> 0.22167038 | C6: =Income_Statement!D6/Income_Statement!B6 -> 0.81999443 | D6: =Income_Statement!I6/Income_Statement!B6 -> 0.41437855 | E6: =Income_Statement!M6/Income_Statement!B6 -> 0.30083696 | F6: =Income_Statement!L6/Income_Statement!K6 -> 0.2964437 | G6: =Income_Statement!E6/Income_Statement!B6 -> 0.28548113 | H6: =Cash_Flow!E6/Income_Statement!B6 -> 0.35933939 | I6: =Cash_Flow!F6/Income_Statement!B6 -> 0.21687748

Sheet Waterfall_2025
A1: Step_Order | B1: Step | C1: Amount | E1: Net income check
A2: 1 | B2: Revenue | C2: 200966 | E2: =SUM(C2:C8) -> 60458 | F2: should equal 60,458 (Income_Statement 2025 Net_Income)
A3: 2 | B3: Cost of revenue | C3: -36175
A4: 3 | B4: Research & development | C4: -57372
A5: 4 | B5: Marketing & sales | C5: -11991
A6: 5 | B6: General & administrative | C6: -12152
A7: 6 | B7: Interest & other income | C7: 2656
A8: 7 | B8: Income tax | C8: -25474

Sheet Dim_Year
A1: Year | B1: Year_Num
A2: 2021 | B2: 2021
A3: 2022 | B3: 2022
A4: 2023 | B4: 2023
A5: 2024 | B5: 2024
A6: 2025 | B6: 2025

Sheet Revenue_Mix
A1: Year | B1: Revenue_Source | C1: Revenue
A2: 2021 | B2: Advertising | C2: 114934
A3: 2021 | B3: Other Family of Apps | C3: 721
A4: 2021 | B4: Reality Labs | C4: 2274
A5: 2022 | B5: Advertising | C5: 113642
A6: 2022 | B6: Other Family of Apps | C6: 808
A7: 2022 | B7: Reality Labs | C7: 2159
A8: 2023 | B8: Advertising | C8: 131948
A9: 2023 | B9: Other Family of Apps | C9: 1058
A10: 2023 | B10: Reality Labs | C10: 1896
A11: 2024 | B11: Advertising | C11: 160633
A12: 2024 | B12: Other Family of Apps | C12: 1722
A13: 2024 | B13: Reality Labs | C13: 2146
... A16: 2025 | B16: Reality Labs | C16: 2207
